{
	"configurations" : 
	[
		{
			"directories" : 
			[
				{
					"build" : ".",
					"jsonFile" : "directory-.-Debug-d0094a50bb2071803777.json",
					"minimumCMakeVersion" : 
					{
						"string" : "4.1"
					},
					"projectIndex" : 0,
					"source" : ".",
					"targetIndexes" : 
					[
						0
					]
				}
			],
			"name" : "Debug",
			"projects" : 
			[
				{
					"directoryIndexes" : 
					[
						0
					],
					"name" : "GetReadyForYourDate",
					"targetIndexes" : 
					[
						0
					]
				}
			],
			"targets" : 
			[
				{
					"directoryIndex" : 0,
					"id" : "GetReadyForYourDate::@6890427a1f51a3e7e1df",
					"jsonFile" : "target-GetReadyForYourDate-Debug-5526b648e178b0b28b23.json",
					"name" : "GetReadyForYourDate",
					"projectIndex" : 0
				}
			]
		}
	],
	"kind" : "codemodel",
	"paths" : 
	{
		"build" : "C:/Users/David/CLionProjects/GetReadyForYourDate/cmake-build-debug",
		"source" : "C:/Users/David/CLionProjects/GetReadyForYourDate"
	},
	"version" : 
	{
		"major" : 2,
		"minor" : 8
	}
}
